pyClients
