Metadata-Version: 1.0
Name: pyClients
Version: 0.1.1
Summary: Clientes (fuente y consumidor) para https://github.com/matias-martinez/internetworking-streaming
Home-page: UNKNOWN
Author: Rodrigo
Author-email: jacznik.rodrigo@gmail.com
License: GPL2
Platform: UNKNOWN
